[
    {
        "cep": "72863-289",
        "logradouro": "Quadra M",
        "bairro": "Chácaras Paulista",
        "cidade": "Novo Gama",
        "estado": "Goiás"
    },
    {
        "cep": "78735-006",
        "logradouro": "Rua A-116",
        "bairro": "Parque Sagrada Família",
        "cidade": "Rondonópolis",
        "estado": "Mato Grosso"
    },
    {
        "cep": "86072-260",
        "logradouro": "Rua Ângelo Gaiotto",
        "bairro": "Santa Rita 1",
        "cidade": "Londrina",
        "estado": "Paraná"
    },
    {
        "cep": "21635-160",
        "logradouro": "Rua Elvio de Moura",
        "bairro": "Ricardo de Albuquerque",
        "cidade": "Rio de Janeiro",
        "estado": "Rio de Janeiro"
    },
    {
        "cep": "69306-705",
        "logradouro": "Avenida Major Williams",
        "bairro": "São Pedro",
        "cidade": "Boa Vista",
        "estado": "Roraima"
    },
    {
        "cep": "89037-515",
        "logradouro": "Rua Vênus",
        "bairro": "Escola Agrícola",
        "cidade": "Blumenau",
        "estado": "Santa Catarina"
    },
    {
        "cep": "49044-311",
        "logradouro": "Travessa B17",
        "bairro": "Santa Maria",
        "cidade": "Aracaju",
        "estado": "Sergipe"
    },
    {
        "cep": "36204-062",
        "logradouro": "Rua Caetés",
        "bairro": "Novo Horizonte",
        "cidade": "Barbacena",
        "estado": "Minas Gerais"
    },
    {
        "cep": "76821-354",
        "logradouro": "Rua Lourival Lira",
        "bairro": "Rio Madeira",
        "cidade": "Porto Velho",
        "estado": "Rondônia"
    },
    {
        "cep": "58090-212",
        "logradouro": "Rua Comerciante José Francisco da Silva",
        "bairro": "Alto do Mateus",
        "cidade": "João Pessoa",
        "estado": "Paraíba"
    }
]